__init__.py
api.py
client.py
debug.py
devices.py
exception.py
manager.py
proxy.py
utils.py
andytele/__init__.py
andytele/api.py
andytele/client.py
andytele/debug.py
andytele/devices.py
andytele/exception.py
andytele/manager.py
andytele/proxy.py
andytele/utils.py
andytele/td/__init__.py
andytele/td/account.py
andytele/td/auth.py
andytele/td/configs.py
andytele/td/mtp.py
andytele/td/shared.py
andytele/td/storage.py
andytele/td/tdesktop.py
andytele/tl/__init__.py
andytele/tl/configs.py
andytele/tl/shared.py
andytele/tl/telethon.py
andytele-1.0.2.dist-info/licenses/LICENSE
ooptele/__init__.py
ooptele/api.py
ooptele/client.py
ooptele/debug.py
ooptele/devices.py
ooptele/exception.py
ooptele/manager.py
ooptele/proxy.py
ooptele/utils.py
ooptele/td/__init__.py
ooptele/td/account.py
ooptele/td/auth.py
ooptele/td/configs.py
ooptele/td/mtp.py
ooptele/td/shared.py
ooptele/td/storage.py
ooptele/td/tdesktop.py
ooptele/tl/__init__.py
ooptele/tl/configs.py
ooptele/tl/shared.py
ooptele/tl/telethon.py
td/__init__.py
td/account.py
td/auth.py
td/configs.py
td/mtp.py
td/shared.py
td/storage.py
td/tdesktop.py
tl/__init__.py
tl/configs.py
tl/shared.py
tl/telethon.py
andytele-1.0.2.dist-info/METADATA
andytele-1.0.2.dist-info/WHEEL
andytele-1.0.2.dist-info/top_level.txt
andytele-1.0.2.dist-info/RECORD
