Metadata-Version: 2.4
Name: andytele
Version: 1.0.2
Home-page: 
Author: 
Author-email: 
License: MIT
Classifier: License :: OSI Approved :: MIT License
Classifier: Operating System :: Microsoft :: Windows
Classifier: Operating System :: MacOS
Classifier: Operating System :: POSIX :: Linux
Classifier: Programming Language :: Python :: 3
Classifier: Programming Language :: Python :: 3.7
Classifier: Development Status :: 5 - Production/Stable
License-File: LICENSE
Requires-Dist: pyqt5
Requires-Dist: telethon
Requires-Dist: tgcrypto
Requires-Dist: python_socks
Dynamic: classifier
Dynamic: description
Dynamic: description-content-type
Dynamic: license
Dynamic: license-file
Dynamic: requires-dist
